{
  "generator-jhipster": {
    "applicationIndex": 2,
    "applicationType": "microservice",
    "authenticationType": "jwt",
    "baseName": "bookApi",
    "blueprints": [],
    "buildTool": "maven",
    "cacheProvider": "ehcache",
    "clientFramework": "no",
    "clientPackageManager": "npm",
    "creationTimestamp": 1695081047669,
    "databaseType": "sql",
    "devDatabaseType": "h2Disk",
    "dtoSuffix": "DTO",
    "enableGradleEnterprise": false,
    "enableHibernateCache": true,
    "enableSwaggerCodegen": false,
    "enableTranslation": true,
    "entities": ["Book", "Customer", "Order", "ShoppingCart"],
    "entitySuffix": "",
    "gradleEnterpriseHost": "",
    "jhiPrefix": "jhi",
    "jhipsterVersion": "7.9.4",
    "jwtSecretKey": "NDM3NDgwODk5Yjg0ZDI1N2IwYzlhMzBkNTNlZDcxYzZjNjBiZDFlYmFiMGQ5ZDQ4OGVmMzg3MDNhYzVlZTgzMjFhMGVkMDdhYjZlMzk5NGNlNmU1ZTI3ZjA5ODJlMmI2YTljYWRhZTA4ODFmM2U0MzcyMzk4YThmNjFjN2I1ZDg=",
    "languages": ["en"],
    "lastLiquibaseTimestamp": 1695081287000,
    "messageBroker": false,
    "microfrontend": false,
    "monorepository": true,
    "nativeLanguage": "en",
    "otherModules": [],
    "packageFolder": "com/bookapi/app",
    "packageName": "com.bookapi.app",
    "pages": [],
    "prodDatabaseType": "postgresql",
    "reactive": false,
    "searchEngine": false,
    "serverPort": "8082",
    "serviceDiscoveryType": "consul",
    "skipCheckLengthOfIdentifier": false,
    "skipClient": true,
    "skipCommitHook": true,
    "skipFakeData": false,
    "skipUserManagement": true,
    "testFrameworks": [],
    "websocket": false,
    "withAdminUi": false
  }
}
